{"name":"data_bag_item_apps_db","json_class":"Chef::DataBagItem","chef_type":"data_bag_item","data_bag":"apps","raw_data":{"id":"db","driver":{"encrypted_data":"AinWEta75o+VMQoWMZKgHasj3rMVfETEnT5qXpHUIkvQJwQm6qxqHBW03+MU\nF8Zv\n","iv":"Q7sXue1DYaBi/ZQY8nPp5Q==\n","version":1,"cipher":"aes-256-cbc"},"url":{"encrypted_data":"TSTGUTghej8bHxFc0ySt93OAc8IP2UbgDLmFmihkSLpNeS2xduVL3bVlcusp\noGdsK2ete+ylWgOrPGwdjb1SFg==\n","iv":"8i5SLZEyYhQXfOKy38dEIg==\n","version":1,"cipher":"aes-256-cbc"},"user":{"encrypted_data":"41AsX1FCvM76AONWoh2fbhpZmGftU+UUnfoXBSsrk/Y=\n","iv":"9i66i2OeaQiUeizYv93Xpw==\n","version":1,"cipher":"aes-256-cbc"},"password":{"encrypted_data":"Nmzwfmlzv+FO/3T1UPLWZpYktn6KZH5cuxGX9ic8VOunNmH6LBJsw53x7reT\nHHku\n","iv":"ZApfsaXXnchbtvmi1UqTPA==\n","version":1,"cipher":"aes-256-cbc"}}}